sbomgencli/main.py
sbomgencli/Parsers/conanParser.py
sbomgencli/Parsers/dartParser.py
sbomgencli/Parsers/dotnetParser.py
sbomgencli/Parsers/gomodParser.py
sbomgencli/Parsers/gradleGroovyParser.py
sbomgencli/Parsers/gradlekotlinDSLParser.py
sbomgencli/Parsers/mavenParser.py
sbomgencli/Parsers/npmParser.py
sbomgencli/Parsers/phpParser.py
sbomgencli/Parsers/requirementsParser.py
sbomgencli/Parsers/rubyParser.py
sbomgencli/Parsers/rustParser.py
sbomgencli/Parsers/swiftParser.py
sbomgencli/Parsers/yarnParser.py
sbomgencli/Utility/dependencyTree.py
sbomgencli/Utility/helpers.py
sbomgencli/Utility/zip.py
sbomgencli-1.0.0.dist-info/License.txt
sbomgencli-1.0.0.dist-info/METADATA
sbomgencli-1.0.0.dist-info/WHEEL
sbomgencli-1.0.0.dist-info/entry_points.txt
sbomgencli-1.0.0.dist-info/top_level.txt
sbomgencli-1.0.0.dist-info/RECORD
